hammocking/__init__.py
hammocking/__main__.py
hammocking/hammocking.ini
hammocking/hammocking.py
hammocking/templates/gmock/mockup.cc.j2
hammocking/templates/gmock/mockup.h.j2
hammocking/templates/plain_c/mockup.c.j2
hammocking/templates/plain_c/mockup.h.j2
hammocking-0.9.0.dist-info/LICENSE
hammocking-0.9.0.dist-info/METADATA
hammocking-0.9.0.dist-info/WHEEL
hammocking-0.9.0.dist-info/RECORD
