Metadata-Version: 2.3
Name: hammocking
Version: 0.9.0
Summary: Create mocks for c-code automatically
License: MIT
Author: Avengineers
Author-email: karsten.guenther@kamg.de
Requires-Python: >=3.10,<3.12
Classifier: Development Status :: 2 - Pre-Alpha
Classifier: Intended Audience :: Developers
Classifier: License :: OSI Approved :: MIT License
Classifier: Natural Language :: English
Classifier: Operating System :: OS Independent
Classifier: Programming Language :: Python :: 3
Classifier: Programming Language :: Python :: 3.10
Classifier: Programming Language :: Python :: 3.11
Classifier: Topic :: Software Development :: Libraries
Requires-Dist: jinja2 (>=3.1.2,<4.0.0)
Requires-Dist: libclang (>=14.0.6,<15.0.0)
Requires-Dist: py-app-dev (>=2.7,<3.0)
Project-URL: Bug Tracker, https://github.com/avengineers/hammocking/issues
Project-URL: Changelog, https://github.com/avengineers/hammocking/blob/develop/CHANGELOG.md
Project-URL: Documentation, https://hammocking.readthedocs.io
Project-URL: Repository, https://github.com/avengineers/hammocking
